aiview/__init__.py
aiview/main.py
aiview/helpers/__init__.py
aiview/helpers/utils.py
code/__init__.py
code/main.py
code/helpers/__init__.py
code/helpers/utils.py
ai_reviewer-1.0.0.dist-info/LICENCE
ai_reviewer-1.0.0.dist-info/METADATA
ai_reviewer-1.0.0.dist-info/WHEEL
ai_reviewer-1.0.0.dist-info/entry_points.txt
ai_reviewer-1.0.0.dist-info/top_level.txt
ai_reviewer-1.0.0.dist-info/RECORD
