Metadata-Version: 2.1
Name: ai-reviewer
Version: 1.0.0
Summary: AI code reviewer
Home-page: https://github.com/BouzianeAminePro/ai-reviewer
Author: Bouziane Amine
Classifier: Programming Language :: Python :: 3
Classifier: License :: OSI Approved :: MIT License
Classifier: Operating System :: OS Independent
Requires-Python: >=3.11
License-File: LICENCE
Requires-Dist: langchain-ollama
